README.md
setup.py
hangman_marking_aicore.egg-info/PKG-INFO
hangman_marking_aicore.egg-info/SOURCES.txt
hangman_marking_aicore.egg-info/dependency_links.txt
hangman_marking_aicore.egg-info/requires.txt
hangman_marking_aicore.egg-info/top_level.txt
hangman_test/__init__.py
hangman_test/ast_parser.py
hangman_test/test_milestone2_p1.py
hangman_test/test_milestone2_p2.py
hangman_test/test_milestone3_p1.py
hangman_test/test_milestone3_p2.py
hangman_test/test_milestone4_p1.py
hangman_test/test_milestone4_p2.py
hangman_test/test_milestone5_p1.py
hangman_test/test_milestone5_p2.py
hangman_test/verify.py
hangman_test/verify_milestone1.py
hangman_test/verify_milestone2_p1.py
hangman_test/verify_milestone2_p2.py
hangman_test/verify_milestone3_p1.py
hangman_test/verify_milestone3_p2.py
hangman_test/verify_milestone4_p1.py
hangman_test/verify_milestone4_p2.py
hangman_test/verify_milestone5_p1.py
hangman_test/verify_milestone5_p2.py