Metadata-Version: 2.1
Name: hangman-marking-aicore
Version: 1.1.23
Summary: An automated marking system for the hangman project (test)
Author: Ivan Ying
Author-email: ivan@theaicore.com
Requires-Python: >=3.6
